DESCRIPTION.rst
MANIFEST.in
README.md
RELEASE-VERSION
setup.cfg
setup.py
version.py
hybridizer/__init__.py
hybridizer/hybridizer.py
hybridizer.egg-info/PKG-INFO
hybridizer.egg-info/SOURCES.txt
hybridizer.egg-info/dependency_links.txt
hybridizer.egg-info/entry_points.txt
hybridizer.egg-info/requires.txt
hybridizer.egg-info/top_level.txt