Metadata-Version: 1.1
Name: hybridizer
Version: 1.02
Summary: Interface to the Janelia hybridizer.
Home-page: https://github.com/janelia-pypi/hybridizer_python
Author: Peter Polidoro
Author-email: polidorop@janelia.hhmi.org
License: BSD
Keywords: hybridizer janelia modular_device bioshake
Platform: UNKNOWN
Classifier: Development Status :: 4 - Beta
Classifier: Intended Audience :: Developers
Classifier: Topic :: Software Development :: Build Tools
Classifier: License :: OSI Approved :: BSD License
Classifier: Programming Language :: Python :: 2.7
